mloptiflow/__init__.py
mloptiflow/cli/__init__.py
mloptiflow/cli/commands/__init__.py
mloptiflow/cli/commands/deploy.py
mloptiflow/cli/commands/init.py
mloptiflow/cli/commands/monitor.py
mloptiflow/cli/commands/plugins.py
mloptiflow/cli/commands/train.py
mloptiflow/cli/utils/__init__.py
mloptiflow/cli/utils/config.py
mloptiflow/cli/utils/templates.py
mloptiflow/deployment/config.py
mloptiflow/mlflow_integration/__init__.py
mloptiflow/mlflow_integration/base.py
mloptiflow/mlflow_integration/tabular.py
mloptiflow/model_registry/registry.py
mloptiflow/monitoring/__init__.py
mloptiflow/monitoring/config.py
mloptiflow/monitoring/consumer/__init__.py
mloptiflow/monitoring/consumer/drift_detector.py
mloptiflow/monitoring/consumer/service.py
mloptiflow/monitoring/factory.py
mloptiflow/monitoring/producer/__init__.py
mloptiflow/monitoring/producer/base_handler.py
mloptiflow/monitoring/producer/tabular_handler.py
mloptiflow/monitoring/ui/__init__.py
mloptiflow/monitoring/ui/app.py
mloptiflow/monitoring/ui/cli.py
mloptiflow/monitoring/ui/consumers.py
mloptiflow/monitoring/ui/state.py
mloptiflow/monitoring/ui/visualizations.py
mloptiflow/monitoring/utils/__init__.py
mloptiflow/monitoring/utils/kafka_manager.py
mloptiflow/monitoring/utils/serialization.py
mloptiflow/templates/__init__.py
mloptiflow/templates/demo_tabular_classification/.gitignore
mloptiflow/templates/demo_tabular_classification/README.md
mloptiflow/templates/demo_tabular_classification/app.py
mloptiflow/templates/demo_tabular_classification/config.yaml
mloptiflow/templates/demo_tabular_classification/data/.gitkeep
mloptiflow/templates/demo_tabular_classification/deployment/.dockerignore
mloptiflow/templates/demo_tabular_classification/deployment/Dockerfile.api
mloptiflow/templates/demo_tabular_classification/deployment/Dockerfile.kafka
mloptiflow/templates/demo_tabular_classification/deployment/docker-compose.yml
mloptiflow/templates/demo_tabular_classification/docs/.gitkeep
mloptiflow-0.1.0.dist-info/LICENSE
mloptiflow-0.1.0.dist-info/METADATA
mloptiflow-0.1.0.dist-info/WHEEL
mloptiflow-0.1.0.dist-info/entry_points.txt
mloptiflow-0.1.0.dist-info/RECORD
