Metadata-Version: 2.1
Name: mloptiflow
Version: 0.1.0
Summary: Dynamic MLOps Framework with Integrated CLI for Automated ML Project Inception, Kafka-Driven Real-Time Model Monitoring, and Adaptive Canary Deployment Architectures
Home-page: https://gitlab.com/mloptiflow/mloptiflow
License: MIT
Author: Tomas Kozak
Author-email: tomas.kozak.inv@gmail.com
Requires-Python: >=3.11,<4.0
Classifier: License :: OSI Approved :: MIT License
Classifier: Programming Language :: Python :: 3
Classifier: Programming Language :: Python :: 3.11
Classifier: Programming Language :: Python :: 3.12
Requires-Dist: PyYAML (>=6.0.2,<7.0.0)
Requires-Dist: aiohttp (>=3.11.11,<4.0.0)
Requires-Dist: click (>=8.1.7,<9.0.0)
Requires-Dist: fastapi (>=0.115.5,<0.116.0)
Requires-Dist: mlflow (>=2.19.0,<3.0.0)
Requires-Dist: pandas (>=2.2.3,<3.0.0)
Requires-Dist: plotly (>=6.0.0,<7.0.0)
Requires-Dist: psutil (>=6.1.1,<7.0.0)
Requires-Dist: pydantic (>=2.10.4,<3.0.0)
Requires-Dist: python-dotenv (>=1.0.0,<2.0.0)
Requires-Dist: quixstreams (>=3.7.0,<4.0.0)
Requires-Dist: scikit-learn (>=1.5.2,<1.6.0)
Requires-Dist: streamlit (>=1.43.1,<2.0.0)
Requires-Dist: tenacity (>=9.0.0,<10.0.0)
Requires-Dist: uvicorn (>=0.32.1,<0.33.0)
Requires-Dist: xgboost (>=2.1.3,<3.0.0)
Project-URL: Repository, https://gitlab.com/mloptiflow/mloptiflow
